dnac_sidekick/__init__.py
dnac_sidekick/cli.py
dnac_sidekick/device_commands/__init__.py
dnac_sidekick/device_commands/commands.py
dnac_sidekick/generate/__init__.py
dnac_sidekick/generate/commands.py
dnac_sidekick/generate/j2_templates/pyats_testbed.j2
dnac_sidekick/health/__init__.py
dnac_sidekick/health/commands.py
dnac_sidekick/helpers/topology.py
dnac_sidekick/inventory/__init__.py
dnac_sidekick/inventory/commands.py
dnac_sidekick/licenses/__init__.py
dnac_sidekick/licenses/commands.py
dnac_sidekick-0.1.3.dist-info/entry_points.txt
dnac_sidekick-0.1.3.dist-info/LICENSE
dnac_sidekick-0.1.3.dist-info/WHEEL
dnac_sidekick-0.1.3.dist-info/METADATA
dnac_sidekick-0.1.3.dist-info/RECORD
