Metadata-Version: 2.1
Name: dnac-sidekick
Version: 0.1.3
Summary: A CLI app used to interact with Cisco DNA Center
Home-page: https://github.com/dannywade/dnac-sidekick
License: MIT
Author: Dan Wade
Author-email: danny.wade35@gmail.com
Requires-Python: >=3.8,<4.0
Classifier: License :: OSI Approved :: MIT License
Classifier: Programming Language :: Python :: 3
Classifier: Programming Language :: Python :: 3.8
Classifier: Programming Language :: Python :: 3.9
Classifier: Programming Language :: Python :: 3.10
Requires-Dist: Jinja2 (>=3.1.2,<4.0.0)
Requires-Dist: PyYAML (>=6.0,<7.0)
Requires-Dist: Pygments (==2.13.0)
Requires-Dist: attrs (==22.1.0)
Requires-Dist: black (==22.8.0)
Requires-Dist: certifi (==2022.6.15.1)
Requires-Dist: charset-normalizer (==2.1.1)
Requires-Dist: click (==8.1.3)
Requires-Dist: commonmark (==0.9.1)
Requires-Dist: coverage (==6.4.4)
Requires-Dist: idna (==3.3)
Requires-Dist: iniconfig (==1.1.1)
Requires-Dist: mypy-extensions (==0.4.3)
Requires-Dist: packaging (==21.3)
Requires-Dist: pathspec (==0.10.1)
Requires-Dist: platformdirs (==2.5.2)
Requires-Dist: pluggy (==1.0.0)
Requires-Dist: py (==1.11.0)
Requires-Dist: pyparsing (==3.0.9)
Requires-Dist: pytest (==7.1.3)
Requires-Dist: pytest-cov (==3.0.0)
Requires-Dist: python-dotenv (==0.21.0)
Requires-Dist: requests (==2.28.1)
Requires-Dist: rich (==12.5.1)
Requires-Dist: tomli (==2.0.1)
Requires-Dist: typing-extensions (==4.3.0)
Requires-Dist: urllib3 (==1.26.12)
